mysql_mimic/__init__.py
mysql_mimic/auth.py
mysql_mimic/charset.py
mysql_mimic/connection.py
mysql_mimic/constants.py
mysql_mimic/context.py
mysql_mimic/control.py
mysql_mimic/errors.py
mysql_mimic/functions.py
mysql_mimic/intercept.py
mysql_mimic/packets.py
mysql_mimic/prepared.py
mysql_mimic/results.py
mysql_mimic/schema.py
mysql_mimic/server.py
mysql_mimic/session.py
mysql_mimic/stream.py
mysql_mimic/types.py
mysql_mimic/utils.py
mysql_mimic/variable_processor.py
mysql_mimic/variables.py
mysql_mimic/version.py
mysql_mimic-2.6.4.dist-info/LICENSE
mysql_mimic-2.6.4.dist-info/METADATA
mysql_mimic-2.6.4.dist-info/WHEEL
mysql_mimic-2.6.4.dist-info/top_level.txt
mysql_mimic-2.6.4.dist-info/RECORD
