Metadata-Version: 2.1
Name: mysql-mimic
Version: 2.6.4
Summary: A python implementation of the mysql server protocol
Home-page: https://github.com/kelsin/mysql-mimic
Author: Christopher Giroir
Author-email: kelsin@valefor.com
License: MIT
Platform: UNKNOWN
Classifier: Development Status :: 3 - Alpha
Classifier: Intended Audience :: Developers
Classifier: Intended Audience :: Science/Research
Classifier: Operating System :: OS Independent
Classifier: Programming Language :: SQL
Classifier: Programming Language :: Python :: 3 :: Only
Requires-Python: >=3.6
License-File: LICENSE
Requires-Dist: sqlglot
Provides-Extra: dev
Requires-Dist: aiomysql; extra == "dev"
Requires-Dist: mypy; extra == "dev"
Requires-Dist: mysql-connector-python; extra == "dev"
Requires-Dist: black; extra == "dev"
Requires-Dist: coverage; extra == "dev"
Requires-Dist: freezegun; extra == "dev"
Requires-Dist: gssapi; extra == "dev"
Requires-Dist: k5test; extra == "dev"
Requires-Dist: pylint; extra == "dev"
Requires-Dist: pytest; extra == "dev"
Requires-Dist: pytest-asyncio; extra == "dev"
Requires-Dist: sphinx; extra == "dev"
Requires-Dist: sqlalchemy; extra == "dev"
Requires-Dist: twine; extra == "dev"
Requires-Dist: wheel; extra == "dev"
Provides-Extra: krb5
Requires-Dist: gssapi; extra == "krb5"
